qbittorrentrpc/__init__.py
qbittorrentrpc/core.py
qbittorrentrpc/utils.py
qbittorrentrpc/__metadata__/DISCLIAIMER.md
qbittorrentrpc/__metadata__/LICENSE
qbittorrentrpc/__metadata__/README.md
qbittorrentrpc/__metadata__/__init__.py
qbittorrentrpc/__metadata__/requirements.txt
qbittorrentrpc-0.0.2.dist-info/METADATA
qbittorrentrpc-0.0.2.dist-info/WHEEL
qbittorrentrpc-0.0.2.dist-info/top_level.txt
qbittorrentrpc-0.0.2.dist-info/RECORD
